ArabicTagger/CRF.py
ArabicTagger/Multi_Head_Attention.py
ArabicTagger/NER.py
ArabicTagger/Tagger.py
ArabicTagger/TextMatcher.py
ArabicTagger/Transformer_Encoder.py
ArabicTagger/__init__.py
ArabicTagger/utils.py
ArabicTagger/dict/alphabets_indx.pkl
ArabicTagger/models/CRF_model_1.pkl
ArabicTagger/models/CRF_model_2.pkl
ArabicTagger/models/Matcher_weights1.pkl
ArabicTagger/tags/tags1.pkl
ArabicTagger/tags/tags2.pkl
ArabicTagger-0.1.1.dist-info/LICENSE
ArabicTagger-0.1.1.dist-info/METADATA
ArabicTagger-0.1.1.dist-info/WHEEL
ArabicTagger-0.1.1.dist-info/top_level.txt
ArabicTagger-0.1.1.dist-info/RECORD
