Metadata-Version: 2.1
Name: ArabicTagger
Version: 0.1.1
Summary: A CRF, Encoder-Transformer layers, and BI-LSTM+CRF model were implemented in Keras with other modules.
Home-page: https://github.com/EslamTarekFarouk/ArabicTagger
Author: Eslam Tarek Farouk
Author-email: cds.eslamtarek96337@alexu.edu.eg
Classifier: Programming Language :: Python :: 3
Classifier: License :: OSI Approved :: MIT License
Classifier: Operating System :: OS Independent
License-File: LICENSE
Requires-Dist: tensorflow ==2.10.0
Requires-Dist: keras ==2.10.0
Requires-Dist: nltk
Requires-Dist: bpemb
Requires-Dist: numpy
